nekonohako/__init__.py
nekonohako/nekonohako.py
nekonohako/test.py
nekonohako/core/__init__.py
nekonohako/core/catbox.py
nekonohako/core/const.py
nekonohako-0.0.2.0.dist-info/LICENSE.md
nekonohako-0.0.2.0.dist-info/METADATA
nekonohako-0.0.2.0.dist-info/WHEEL
nekonohako-0.0.2.0.dist-info/top_level.txt
nekonohako-0.0.2.0.dist-info/RECORD
